odoo8_addon_product_standard_price_tax_included-8.0.2.1.0-py2.7-nspkg.pth
odoo8_addon_product_standard_price_tax_included-8.0.2.1.0.dist-info/METADATA
odoo8_addon_product_standard_price_tax_included-8.0.2.1.0.dist-info/RECORD
odoo8_addon_product_standard_price_tax_included-8.0.2.1.0.dist-info/WHEEL
odoo8_addon_product_standard_price_tax_included-8.0.2.1.0.dist-info/namespace_packages.txt
odoo8_addon_product_standard_price_tax_included-8.0.2.1.0.dist-info/top_level.txt
odoo_addons/product_standard_price_tax_included/README.rst
odoo_addons/product_standard_price_tax_included/__init__.py
odoo_addons/product_standard_price_tax_included/__openerp__.py
odoo_addons/product_standard_price_tax_included/data/product_price_type.xml
odoo_addons/product_standard_price_tax_included/demo/account_tax.xml
odoo_addons/product_standard_price_tax_included/demo/product_pricelist.xml
odoo_addons/product_standard_price_tax_included/demo/product_template.xml
odoo_addons/product_standard_price_tax_included/demo/res_groups.xml
odoo_addons/product_standard_price_tax_included/demo/res_partner.xml
odoo_addons/product_standard_price_tax_included/i18n/de.po
odoo_addons/product_standard_price_tax_included/i18n/es.po
odoo_addons/product_standard_price_tax_included/i18n/fr.po
odoo_addons/product_standard_price_tax_included/i18n/product_standard_price_tax_included.pot
odoo_addons/product_standard_price_tax_included/i18n/sl.po
odoo_addons/product_standard_price_tax_included/models/__init__.py
odoo_addons/product_standard_price_tax_included/models/product_template.py
odoo_addons/product_standard_price_tax_included/readme/CONFIGURE.rst
odoo_addons/product_standard_price_tax_included/readme/CONTRIBUTORS.rst
odoo_addons/product_standard_price_tax_included/readme/CREDITS.rst
odoo_addons/product_standard_price_tax_included/readme/DESCRIPTION.rst
odoo_addons/product_standard_price_tax_included/readme/USAGE.rst
odoo_addons/product_standard_price_tax_included/static/description/icon.png
odoo_addons/product_standard_price_tax_included/static/description/index.html
odoo_addons/product_standard_price_tax_included/static/description/pricelist.png
odoo_addons/product_standard_price_tax_included/static/description/product_template.png
odoo_addons/product_standard_price_tax_included/tests/__init__.py
odoo_addons/product_standard_price_tax_included/tests/test_module.py
