Metadata-Version: 2.1
Name: odoo8-addon-product-standard-price-tax-included
Version: 8.0.2.1.0
Summary: Brings a Cost Price Field Tax Included on Product Model
Home-page: http://www.odoo-community.org
Author: GRAP,Odoo Community Association (OCA)
Author-email: support@odoo-community.org
License: AGPL-3
Platform: UNKNOWN
Classifier: Programming Language :: Python
Classifier: Framework :: Odoo
Classifier: License :: OSI Approved :: GNU Affero General Public License v3
Classifier: Development Status :: 4 - Beta
Requires-Python: ~=2.7
Requires-Dist: odoo (<9.0a,>=8.0a)
